energypriceapi/__init__.py
energypriceapi/client.py
energypriceapi-1.0.3.dist-info/LICENSE
energypriceapi-1.0.3.dist-info/METADATA
energypriceapi-1.0.3.dist-info/WHEEL
energypriceapi-1.0.3.dist-info/top_level.txt
energypriceapi-1.0.3.dist-info/RECORD
