Metadata-Version: 2.1
Name: energypriceapi
Version: 1.0.3
Summary: Official Python wrapper for energypriceapi.com
Home-page: https://github.com/energypriceapi/energypriceapi-python
Author: EnergypriceAPI
Author-email: contact@energypriceapi.com
Keywords: currency,oilpriceapi,oil price,foreign exchange rate,currency conversion,exchangerate,rates
License-File: LICENSE
Requires-Dist: requests (>=2.9.1)
